pdf_generator/__main__.py
pdf_generator/convert.py
json2pdf-0.2.dist-info/METADATA
json2pdf-0.2.dist-info/WHEEL
json2pdf-0.2.dist-info/top_level.txt
json2pdf-0.2.dist-info/RECORD
