Metadata-Version: 2.1
Name: json2pdf
Version: 0.2
Requires-Dist: pandas
Requires-Dist: jinja2
Requires-Dist: PyPDF2
Requires-Dist: pdfkit
